barry_energy/__init__.py
python_barry_energy-0.0.5.dist-info/METADATA
python_barry_energy-0.0.5.dist-info/WHEEL
python_barry_energy-0.0.5.dist-info/top_level.txt
python_barry_energy-0.0.5.dist-info/RECORD
