Metadata-Version: 2.1
Name: python-barry-energy
Version: 0.0.5
Summary: Interfaces with Barry Energy's API
Home-page: http://github.com/Frankkkkk/python-barry-energy
Author: Frank Villaro-Dixon
Author-email: frank@villaro-dixon.eu
License: MIT
Keywords: python barry energy api electricity spot
Platform: UNKNOWN
Classifier: Development Status :: 3 - Alpha
Classifier: Topic :: Utilities
Classifier: License :: OSI Approved :: MIT License
Requires-Dist: requests
